oprf/__init__.py
oprf/oprf.py
oprf-5.0.0.dist-info/LICENSE
oprf-5.0.0.dist-info/METADATA
oprf-5.0.0.dist-info/WHEEL
oprf-5.0.0.dist-info/top_level.txt
oprf-5.0.0.dist-info/RECORD
