Metadata-Version: 2.1
Name: oprf
Version: 5.0.0
Summary: Oblivious pseudo-random function (OPRF) protocol functionality implementations based on Curve25519 and the Ristretto group.
Author: Andrei Lapets
Author-email: a@lapets.io
License: MIT
Project-URL: Repository, https://github.com/nthparty/oprf
Project-URL: Documentation, https://oprf.readthedocs.io
Requires-Python: >=3.7
License-File: LICENSE
Requires-Dist: oblivious[rbcl] (~=7.0)
Provides-Extra: coveralls
Requires-Dist: coveralls (~=3.3.1) ; extra == 'coveralls'
Provides-Extra: docs
Requires-Dist: toml (~=0.10.2) ; extra == 'docs'
Requires-Dist: sphinx (~=4.2.0) ; extra == 'docs'
Requires-Dist: sphinx-rtd-theme (~=1.0.0) ; extra == 'docs'
Provides-Extra: lint
Requires-Dist: pylint (~=2.17.0) ; extra == 'lint'
Provides-Extra: publish
Requires-Dist: build (~=0.10) ; extra == 'publish'
Requires-Dist: twine (~=4.0) ; extra == 'publish'
Provides-Extra: test
Requires-Dist: pytest (~=7.2) ; extra == 'test'
Requires-Dist: pytest-cov (~=4.0) ; extra == 'test'
